chain_reaction/__init__.py
chain_reaction/chain_reaction.py
chain_reaction/chain_reaction_pygame.py
dumbbots-0.0.1.dist-info/METADATA
dumbbots-0.0.1.dist-info/WHEEL
dumbbots-0.0.1.dist-info/top_level.txt
dumbbots-0.0.1.dist-info/RECORD
