Metadata-Version: 2.1
Name: dumbbots
Version: 0.0.1
Summary: Universal package for all the dumb things which we bots do
Author-email: Dead Developers Society <deaddevelopersociety@gmail.com>
Project-URL: Homepage, https://github.com/DDSociety/DumbBots
Provides-Extra: dev
Requires-Dist: pygame; extra == "dev"
